biocompart/__init__.py
biocompart-0.1.0.dist-info/licenses/LICENSE
biocompart-0.1.0.dist-info/METADATA
biocompart-0.1.0.dist-info/WHEEL
biocompart-0.1.0.dist-info/top_level.txt
biocompart-0.1.0.dist-info/RECORD
