Metadata-Version: 2.4
Name: biocompart
Version: 0.1.0
Summary: Add your description here
Requires-Python: >=3.10
License-File: LICENSE
Requires-Dist: polars>=1.25.2
Dynamic: license-file
